ytdl.py
ytdl_interactive-1.1.2.dist-info/licenses/LICENSE
ytdl_interactive-1.1.2.dist-info/METADATA
ytdl_interactive-1.1.2.dist-info/WHEEL
ytdl_interactive-1.1.2.dist-info/entry_points.txt
ytdl_interactive-1.1.2.dist-info/top_level.txt
ytdl_interactive-1.1.2.dist-info/RECORD
