Metadata-Version: 2.4
Name: ytdl-interactive
Version: 1.1.2
Summary: Interactive YouTube Downloader CLI powered by yt-dlp
Author-email: ytdl Contributors <ytdl@example.com>
License-Expression: MIT
Project-URL: Homepage, https://github.com/abd3lraouf/ytdl
Project-URL: Repository, https://github.com/abd3lraouf/ytdl
Project-URL: Issues, https://github.com/abd3lraouf/ytdl/issues
Project-URL: Documentation, https://github.com/abd3lraouf/ytdl#readme
Keywords: youtube,downloader,cli,yt-dlp,interactive,video,playlist
Classifier: Development Status :: 5 - Production/Stable
Classifier: Environment :: Console
Classifier: Intended Audience :: End Users/Desktop
Classifier: Operating System :: OS Independent
Classifier: Programming Language :: Python :: 3
Classifier: Programming Language :: Python :: 3.9
Classifier: Programming Language :: Python :: 3.10
Classifier: Programming Language :: Python :: 3.11
Classifier: Programming Language :: Python :: 3.12
Classifier: Topic :: Multimedia :: Video
Requires-Python: >=3.9
License-File: LICENSE
Requires-Dist: yt-dlp>=2024.1.0
Requires-Dist: questionary>=2.0.0
Provides-Extra: dev
Requires-Dist: pytest>=7.0.0; extra == "dev"
Requires-Dist: black>=23.0.0; extra == "dev"
Requires-Dist: mypy>=1.0.0; extra == "dev"
Dynamic: license-file
